dogcputils/__init__.py
dogcputils/gcp_utilities.py
dogcputils/logger_wrapper.py
utilities/__init__.py
utilities/gcp_utilities.py
utilities/logger_wrapper.py
dogcputils-1.0.7.dist-info/METADATA
dogcputils-1.0.7.dist-info/WHEEL
dogcputils-1.0.7.dist-info/top_level.txt
dogcputils-1.0.7.dist-info/RECORD
