Metadata-Version: 2.1
Name: dogcputils
Version: 1.0.7
Summary: A core repository of do utilities class. change source directory to dogcputils
Home-page: https://github.com/Deep-Ocean-Fund/do-core
Author: Prawit Pimmasarn
Author-email: prawit.pimmasarn@gmail.com
License: MIT
Classifier: Programming Language :: Python :: 3.9
Classifier: License :: OSI Approved :: MIT License
Classifier: Operating System :: OS Independent
Requires-Python: >=3.9
